<?xml version="1.0" encoding="utf-8" ?><dwsync><file name="Archives.jpg" server="mckenziepta.com" local="3363742800" remote="20543611984" /><file name="BookFair.jpg" server="mckenziepta.com" local="3364779600" remote="20544648784" /><file name="CRC.jpg" server="mckenziepta.com" local="3363742800" remote="20543611984" /><file name="CafeteriaDuty.jpg" server="mckenziepta.com" local="3370741200" remote="20550610384" /><file name="Calendar.jpg" server="mckenziepta.com" local="3366075600" remote="20545944784" /><file name="ChessClub.jpg" server="mckenziepta.com" local="3365211600" remote="20545080784" /><file name="CivicsSafety.jpg" server="mckenziepta.com" local="3363742800" remote="20543611984" /><file name="Clubs.jpg" server="mckenziepta.com" local="3363742800" remote="20543611984" /><file name="Communication.jpg" server="mckenziepta.com" local="3363742800" remote="20543611984" /><file name="Communications.jpg" server="mckenziepta.com" local="3370741200" remote="20550610384" /><file name="District39.jpg" server="mckenziepta.com" local="3364088400" remote="20543957584" /><file name="District39Foundation.jpg" server="mckenziepta.com" local="3363742800" remote="20543611984" /><file name="Enrichment.jpg" server="mckenziepta.com" local="3370741200" remote="20550610384" /><file name="FAN.jpg" server="mckenziepta.com" local="3370741200" remote="20550610384" /><file name="FineArts.jpg" server="mckenziepta.com" local="3363742800" remote="20543611984" /><file name="GroceryDollars.jpg" server="mckenziepta.com" local="3363742800" remote="20543611984" /><file name="IceCreamSocial.jpg" server="mckenziepta.com" local="3365470800" remote="20545339984" /><file name="LecturesMeetings.jpg" server="mckenziepta.com" local="3363742800" remote="20543611984" /><file name="LunchMenu.jpg" server="mckenziepta.com" local="3363742800" remote="20543611984" /><file name="McClubs.jpg" server="mckenziepta.com" local="3370741200" remote="20550610384" /><file name="McKenzieMingle.jpg" server="mckenziepta.com" local="3370741200" remote="20550610384" /><file name="McKenzieSchool.jpg" server="mckenziepta.com" local="3364088400" remote="20543957584" /><file name="Merchandising.jpg" server="mckenziepta.com" local="3367026000" remote="20546895184" /><file name="Monitor.jpg" server="mckenziepta.com" local="3365902800" remote="20545771984" /><file name="OutdoorClass.jpg" server="mckenziepta.com" local="3363742800" remote="20543611984" /><file name="PLN.jpg" server="mckenziepta.com" local="3366939600" remote="20546808784" /><file name="PTA.jpg" server="mckenziepta.com" local="3368926800" remote="20548795984" /><file name="PTAmembership.jpg" server="mckenziepta.com" local="3363742800" remote="20543611984" /><file name="PlaceHolder.jpg" server="mckenziepta.com" local="3363742800" remote="20543611984" /><file name="Schools.jpg" server="mckenziepta.com" local="3363742800" remote="20543611984" /><file name="Sharing.jpg" server="mckenziepta.com" local="3366939600" remote="20546808784" /><file name="ShopPay.jpg" server="mckenziepta.com" local="3363742800" remote="20543611984" /><file name="Thumbs.db" server="mckenziepta.com" local="3363742800" remote="20543611984" /><file name="right_bar.psd" server="mckenziepta.com" local="3365902800" remote="20545771984" /></dwsync>