<?xml version="1.0" encoding="utf-8" ?><dwsync><file name=".DS_Store" server="mckenziepta.com" local="3428355134" remote="12018307772" Dst="-1" /><file name="august_september.pdf" server="mckenziepta.com" local="3428355018" remote="12018307772" Dst="-1" /><file name="october.pdf" server="mckenziepta.com" local="3431005181" remote="319519907823830020" Dst="-1" /><file name="november.pdf" server="ftp.mckenziepta.com" local="3433766242" remote="319519907826590860" Dst="-1" /><file name="december.pdf" server="ftp.mckenziepta.com" local="3436878711" remote="319519907829681520" Dst="-1" /><file name="january.pdf" server="ftp.mckenziepta.com" local="3438187394" remote="319519907830990240" Dst="-1" /><file name="february.pdf" server="ftp.mckenziepta.com" local="3441798677" remote="319519907834651620" Dst="-1" /><file name="march.pdf" server="ftp.mckenziepta.com" local="3444852987" remote="319519907837655820" Dst="-1" /><file name="april.pdf" server="ftp.mckenziepta.com" local="3446589570" remote="319519907839388740" Dst="-1" /><file name="may.pdf" server="ftp.mckenziepta.com" local="3449585105" remote="319519907842384300" Dst="-1" /><file name="june.pdf" server="ftp.mckenziepta.com" local="3451999686" remote="319519907844798880" Dst="-1" /></dwsync>